slack_bolt/__init__.py
slack_bolt/async_app.py
slack_bolt/py.typed
slack_bolt/version.py
slack_bolt/adapter/__init__.py
slack_bolt/adapter/aiohttp/__init__.py
slack_bolt/adapter/asgi/__init__.py
slack_bolt/adapter/asgi/async_handler.py
slack_bolt/adapter/asgi/base_handler.py
slack_bolt/adapter/asgi/http_request.py
slack_bolt/adapter/asgi/http_response.py
slack_bolt/adapter/asgi/utils.py
slack_bolt/adapter/asgi/aiohttp/__init__.py
slack_bolt/adapter/asgi/builtin/__init__.py
slack_bolt/adapter/aws_lambda/__init__.py
slack_bolt/adapter/aws_lambda/chalice_handler.py
slack_bolt/adapter/aws_lambda/chalice_lazy_listener_runner.py
slack_bolt/adapter/aws_lambda/handler.py
slack_bolt/adapter/aws_lambda/internals.py
slack_bolt/adapter/aws_lambda/lambda_s3_oauth_flow.py
slack_bolt/adapter/aws_lambda/lazy_listener_runner.py
slack_bolt/adapter/aws_lambda/local_lambda_client.py
slack_bolt/adapter/bottle/__init__.py
slack_bolt/adapter/bottle/handler.py
slack_bolt/adapter/cherrypy/__init__.py
slack_bolt/adapter/cherrypy/handler.py
slack_bolt/adapter/django/__init__.py
slack_bolt/adapter/django/handler.py
slack_bolt/adapter/falcon/__init__.py
slack_bolt/adapter/falcon/async_resource.py
slack_bolt/adapter/falcon/resource.py
slack_bolt/adapter/fastapi/__init__.py
slack_bolt/adapter/fastapi/async_handler.py
slack_bolt/adapter/flask/__init__.py
slack_bolt/adapter/flask/handler.py
slack_bolt/adapter/google_cloud_functions/__init__.py
slack_bolt/adapter/google_cloud_functions/handler.py
slack_bolt/adapter/pyramid/__init__.py
slack_bolt/adapter/pyramid/handler.py
slack_bolt/adapter/sanic/__init__.py
slack_bolt/adapter/sanic/async_handler.py
slack_bolt/adapter/socket_mode/__init__.py
slack_bolt/adapter/socket_mode/async_base_handler.py
slack_bolt/adapter/socket_mode/async_handler.py
slack_bolt/adapter/socket_mode/async_internals.py
slack_bolt/adapter/socket_mode/base_handler.py
slack_bolt/adapter/socket_mode/internals.py
slack_bolt/adapter/socket_mode/aiohttp/__init__.py
slack_bolt-1.21.2.dist-info/LICENSE
slack_bolt-1.21.2.dist-info/METADATA
slack_bolt-1.21.2.dist-info/WHEEL
slack_bolt-1.21.2.dist-info/top_level.txt
slack_bolt-1.21.2.dist-info/RECORD
