Metadata-Version: 2.1
Name: slack_bolt
Version: 1.21.2
Summary: The Bolt Framework for Python
Home-page: https://github.com/slackapi/bolt-python
Author: Slack Technologies, LLC
Author-email: opensource@slack.com
License: MIT
Project-URL: Documentation, https://slack.dev/bolt-python
Classifier: Programming Language :: Python :: 3.6
Classifier: Programming Language :: Python :: 3.7
Classifier: Programming Language :: Python :: 3.8
Classifier: Programming Language :: Python :: 3.9
Classifier: Programming Language :: Python :: 3.10
Classifier: Programming Language :: Python :: 3.11
Classifier: Programming Language :: Python :: 3.12
Classifier: Programming Language :: Python :: Implementation :: CPython
Classifier: License :: OSI Approved :: MIT License
Classifier: Operating System :: OS Independent
Requires-Python: >=3.6
License-File: LICENSE
Requires-Dist: slack_sdk<4,>=3.33.1
